Workbook

Sheet ROI_Analysis
B2: MEDICAL EQUIPMENT ROI ANALYSIS - 2023 | T2: 📋 ABOUT THIS ANALYSIS
B4: ASSUMPTIONS & INPUTS | T4: Medical Equipment Utilization Data
T5: 36 daily records from 2023
B6: Discount Rate (%) | C6: 0.1 | T6: 0
B7: Target ROI (%) | C7: 0.25 | T7: Key Metrics:
T8: • Daily Operating Cost
B9: PROJECT DATA | M9: PIVOT: ROI BY EQUIPMENT TYPE | T9: • Procedure Revenue
T10: • Net Profit (Daily)
B11: Date | C11: Equipment ID | D11: Equipment Type | E11: Department | F11: Daily Operating Cost | G11: Procedure Revenue | H11: Net Profit (Daily) | I11: Utilization Rate | J11: ROI % | K11: ROI Status | N11: Total Operating Cost | O11: Total Revenue | P11: Total Profit | Q11: Avg ROI % | T11: • Utilization Rate
B12: 12/22/2023 | C12: MRI_0001 | D12: MRI Scanner | E12: Radiology | F12: 5000 | G12: 30000 | H12: 25000 | I12: 0.04 | J12: =IF(F12=0,0,H12/F12) -> 5 | K12: =IF(J12>=$C$7,"Exceeds Target",IF(J12>=0,"Positive","Negative")) -> Exceeds Target | M12: CT Scanner | N12: 1680000 | O12: 101220000 | P12: 99540000 | Q12: 59.25 | T12: • ROI % (Profit/Operating Cost)
B13: 1/24/2023 | C13: XRAY_0002 | D13: X-Ray Machine | E13: Radiology | F13: 1500 | G13: 40000 | H13: 38500 | I13: 0.71 | J13: =IF(F13=0,0,H13/F13) -> 25.666667 | K13: =IF(J13>=$C$7,"Exceeds Target",IF(J13>=0,"Positive","Negative")) -> Exceeds Target | M13: Mammography Unit | N13: 656000 | O13: 58975000 | P13: 58319000 | Q13: 88.900915 | T13: 0
B14: 12/19/2023 | C14: CT_0003 | D14: CT Scanner | E14: Radiology | F14: 3000 | G14: 70000 | H14: 67000 | I14: 0.84 | J14: =IF(F14=0,0,H14/F14) -> 22.333333 | K14: =IF(J14>=$C$7,"Exceeds Target",IF(J14>=0,"Positive","Negative")) -> Exceeds Target | M14: MRI Scanner | N14: 3005000 | O14: 54930000 | P14: 51925000 | Q14: 17.279534 | T14: Equipment Types:
B15: 12/12/2023 | C15: CT_0004 | D15: CT Scanner | E15: Radiology | F15: 3000 | G15: 200000 | H15: 197000 | I15: 0.51 | J15: =IF(F15=0,0,H15/F15) -> 65.666667 | K15: =IF(J15>=$C$7,"Exceeds Target",IF(J15>=0,"Positive","Negative")) -> Exceeds Target | M15: Ultrasound | N15: 588000 | O15: 47547000 | P15: 46959000 | Q15: 79.862245 | T15: • MRI Scanner
B16: 12/31/2023 | C16: XRAY_0005 | D16: X-Ray Machine | E16: Radiology | F16: 1500 | G16: 44000 | H16: 42500 | I16: 0.75 | J16: =IF(F16=0,0,H16/F16) -> 28.333333 | K16: =IF(J16>=$C$7,"Exceeds Target",IF(J16>=0,"Positive","Negative")) -> Exceeds Target | M16: X-Ray Machine | N16: 892500 | O16: 22092000 | P16: 21199500 | Q16: 23.752941 | T16: • CT Scanner
B17: 1/19/2023 | C17: MRI_0006 | D17: MRI Scanner | E17: Radiology | F17: 5000 | G17: 120000 | H17: 115000 | I17: 0.38 | J17: =IF(F17=0,0,H17/F17) -> 23 | K17: =IF(J17>=$C$7,"Exceeds Target",IF(J17>=0,"Positive","Negative")) -> Exceeds Target | M17: Grand Total | N17: 6821500 | O17: 284764000 | P17: 277942500 | Q17: 54.325333 | T17: • X-Ray Machine
B18: 8/16/2023 | C18: MRI_0007 | D18: MRI Scanner | E18: Radiology | F18: 5000 | G18: 30000 | H18: 25000 | I18: 0.17 | J18: =IF(F18=0,0,H18/F18) -> 5 | K18: =IF(J18>=$C$7,"Exceeds Target",IF(J18>=0,"Positive","Negative")) -> Exceeds Target | T18: • Mammography Unit
B19: 2/20/2023 | C19: CT_0008 | D19: CT Scanner | E19: Radiology | F19: 3000 | G19: 100000 | H19: 97000 | I19: 0.7 | J19: =IF(F19=0,0,H19/F19) -> 32.333333 | K19: =IF(J19>=$C$7,"Exceeds Target",IF(J19>=0,"Positive","Negative")) -> Exceeds Target | T19: 0
B20: 10/20/2023 | C20: MRI_0009 | D20: MRI Scanner | E20: Radiology | F20: 5000 | G20: 90000 | H20: 85000 | I20: 0.15 | J20: =IF(F20=0,0,H20/F20) -> 17 | K20: =IF(J20>=$C$7,"Exceeds Target",IF(J20>=0,"Positive","Negative")) -> Exceeds Target | T20: Departments:
B21: 4/26/2023 | C21: MRI_0010 | D21: MRI Scanner | E21: Radiology | F21: 5000 | G21: 150000 | H21: 145000 | I21: 0.25 | J21: =IF(F21=0,0,H21/F21) -> 29 | K21: =IF(J21>=$C$7,"Exceeds Target",IF(J21>=0,"Positive","Negative")) -> Exceeds Target | M21: PIVOT: ROI BY DEPARTMENT | T21: • Radiology
B22: 5/6/2023 | C22: CT_0011 | D22: CT Scanner | E22: Radiology | F22: 3000 | G22: 140000 | H22: 137000 | I22: 0.36 | J22: =IF(F22=0,0,H22/F22) -> 45.666667 | K22: =IF(J22>=$C$7,"Exceeds Target",IF(J22>=0,"Positive","Negative")) -> Exceeds Target | T22: • Women's Health
B23: 6/2/2023 | C23: MRI_0012 | D23: MRI Scanner | E23: Radiology | F23: 5000 | G23: 90000 | H23: 85000 | I23: 0.15 | J23: =IF(F23=0,0,H23/F23) -> 17 | K23: =IF(J23>=$C$7,"Exceeds Target",IF(J23>=0,"Positive","Negative")) -> Exceeds Target | N23: Total Operating Cost | O23: Total Revenue | P23: Avg Utilization
B24: 8/13/2023 | C24: MRI_0013 | D24: MRI Scanner | E24: Radiology | F24: 5000 | G24: 30000 | H24: 25000 | I24: 0.19 | J24: =IF(F24=0,0,H24/F24) -> 5 | K24: =IF(J24>=$C$7,"Exceeds Target",IF(J24>=0,"Positive","Negative")) -> Exceeds Target | M24: Radiology | N24: 6165500 | O24: 225789000 | P24: 0.55358362
B25: 3/12/2023 | C25: CT_0014 | D25: CT Scanner | E25: Radiology | F25: 3000 | G25: 270000 | H25: 267000 | I25: 0.59 | J25: =IF(F25=0,0,H25/F25) -> 89 | K25: =IF(J25>=$C$7,"Exceeds Target",IF(J25>=0,"Positive","Negative")) -> Exceeds Target | M25: Women's Health | N25: 656000 | O25: 58975000 | P25: 0.62378049
B26: 5/27/2023 | C26: MAMMO_0015 | D26: Mammography Unit | E26: Women's Health | F26: 1000 | G26: 105000 | H26: 104000 | I26: 0.82 | J26: =IF(F26=0,0,H26/F26) -> 104 | K26: =IF(J26>=$C$7,"Exceeds Target",IF(J26>=0,"Positive","Negative")) -> Exceeds Target | M26: Grand Total | N26: 6821500 | O26: 284764000 | P26: 0.56893333
B27: 8/16/2023 | C27: MAMMO_0016 | D27: Mammography Unit | E27: Women's Health | F27: 1000 | G27: 110000 | H27: 109000 | I27: 0.5 | J27: =IF(F27=0,0,H27/F27) -> 109 | K27: =IF(J27>=$C$7,"Exceeds Target",IF(J27>=0,"Positive","Negative")) -> Exceeds Target
B28: 2/16/2023 | C28: CT_0017 | D28: CT Scanner | E28: Radiology | F28: 3000 | G28: 250000 | H28: 247000 | I28: 0.42 | J28: =IF(F28=0,0,H28/F28) -> 82.333333 | K28: =IF(J28>=$C$7,"Exceeds Target",IF(J28>=0,"Positive","Negative")) -> Exceeds Target
B29: 11/2/2023 | C29: CT_0018 | D29: CT Scanner | E29: Radiology | F29: 3000 | G29: 180000 | H29: 177000 | I29: 0.88 | J29: =IF(F29=0,0,H29/F29) -> 59 | K29: =IF(J29>=$C$7,"Exceeds Target",IF(J29>=0,"Positive","Negative")) -> Exceeds Target
B30: 5/24/2023 | C30: MAMMO_0019 | D30: Mammography Unit | E30: Women's Health | F30: 1000 | G30: 145000 | H30: 144000 | I30: 0.66 | J30: =IF(F30=0,0,H30/F30) -> 144 | K30: =IF(J30>=$C$7,"Exceeds Target",IF(J30>=0,"Positive","Negative")) -> Exceeds Target
B31: 4/5/2023 | C31: US_0020 | D31: Ultrasound | E31: Radiology | F31: 1000 | G31: 54000 | H31: 53000 | I31: 0.88 | J31: =IF(F31=0,0,H31/F31) -> 53 | K31: =IF(J31>=$C$7,"Exceeds Target",IF(J31>=0,"Positive","Negative")) -> Exceeds Target
B32: 9/29/2023 | C32: US_0021 | D32: Ultrasound | E32: Radiology | F32: 1000 | G32: 108000 | H32: 107000 | I32: 0.79 | J32: =IF(F32=0,0,H32/F32) -> 107 | K32: =IF(J32>=$C$7,"Exceeds Target",IF(J32>=0,"Positive","Negative")) -> Exceeds Target | O32: Total Profit | P32: Avg ROI % | Q32: Avg Utilization
B33: 8/1/2023 | C33: MAMMO_0022 | D33: Mammography Unit | E33: Women's Health | F33: 1000 | G33: 50000 | H33: 49000 | I33: 0.52 | J33: =IF(F33=0,0,H33/F33) -> 49 | K33: =IF(J33>=$C$7,"Exceeds Target",IF(J33>=0,"Positive","Negative")) -> Exceeds Target | M33: CT Scanner | N33: Radiology | O33: 99540000 | P33: 59.25 | Q33: 0.61048214
B34: 6/16/2023 | C34: MRI_0023 | D34: MRI Scanner | E34: Radiology | F34: 5000 | G34: 60000 | H34: 55000 | I34: 0.17 | J34: =IF(F34=0,0,H34/F34) -> 11 | K34: =IF(J34>=$C$7,"Exceeds Target",IF(J34>=0,"Positive","Negative")) -> Exceeds Target | M34: CT Scanner Total | O34: 99540000 | P34: 59.25 | Q34: 0.61048214
B35: 12/29/2023 | C35: MAMMO_0024 | D35: Mammography Unit | E35: Women's Health | F35: 1000 | G35: 90000 | H35: 89000 | I35: 0.45 | J35: =IF(F35=0,0,H35/F35) -> 89 | K35: =IF(J35>=$C$7,"Exceeds Target",IF(J35>=0,"Positive","Negative")) -> Exceeds Target | M35: Mammography Unit | N35: Women's Health | O35: 58319000 | P35: 88.900915 | Q35: 0.62378049
B36: 10/2/2023 | C36: MAMMO_0025 | D36: Mammography Unit | E36: Women's Health | F36: 1000 | G36: 100000 | H36: 99000 | I36: 0.93 | J36: =IF(F36=0,0,H36/F36) -> 99 | K36: =IF(J36>=$C$7,"Exceeds Target",IF(J36>=0,"Positive","Negative")) -> Exceeds Target | M36: Mammography Unit Total | O36: 58319000 | P36: 88.900915 | Q36: 0.62378049
B37: 5/4/2023 | C37: MAMMO_0026 | D37: Mammography Unit | E37: Women's Health | F37: 1000 | G37: 135000 | H37: 134000 | I37: 0.33 | J37: =IF(F37=0,0,H37/F37) -> 134 | K37: =IF(J37>=$C$7,"Exceeds Target",IF(J37>=0,"Positive","Negative")) -> Exceeds Target | M37: MRI Scanner | N37: Radiology | O37: 51925000 | P37: 17.279534 | Q37: 0.19204659
B38: 8/8/2023 | C38: US_0027 | D38: Ultrasound | E38: Radiology | F38: 1000 | G38: 84000 | H38: 83000 | I38: 0.94 | J38: =IF(F38=0,0,H38/F38) -> 83 | K38: =IF(J38>=$C$7,"Exceeds Target",IF(J38>=0,"Positive","Negative")) -> Exceeds Target | M38: MRI Scanner Total | O38: 51925000 | P38: 17.279534 | Q38: 0.19204659
B39: 8/27/2023 | C39: MAMMO_0028 | D39: Mammography Unit | E39: Women's Health | F39: 1000 | G39: 60000 | H39: 59000 | I39: 0.42 | J39: =IF(F39=0,0,H39/F39) -> 59 | K39: =IF(J39>=$C$7,"Exceeds Target",IF(J39>=0,"Positive","Negative")) -> Exceeds Target | M39: Ultrasound | N39: Radiology | O39: 46959000 | P39: 79.862245 | Q39: 0.80302721
B40: 3/3/2023 | C40: US_0029 | D40: Ultrasound | E40: Radiology | F40: 1000 | G40: 60000 | H40: 59000 | I40: 0.84 | J40: =IF(F40=0,0,H40/F40) -> 59 | K40: =IF(J40>=$C$7,"Exceeds Target",IF(J40>=0,"Positive","Negative")) -> Exceeds Target | M40: Ultrasound Total | O40: 46959000 | P40: 79.862245 | Q40: 0.80302721
B41: 12/6/2023 | C41: CT_0030 | D41: CT Scanner | E41: Radiology | F41: 3000 | G41: 300000 | H41: 297000 | I41: 0.53 | J41: =IF(F41=0,0,H41/F41) -> 99 | K41: =IF(J41>=$C$7,"Exceeds Target",IF(J41>=0,"Positive","Negative")) -> Exceeds Target | M41: X-Ray Machine | N41: Radiology | O41: 21199500 | P41: 23.752941 | Q41: 0.61870588
B42: 1/11/2023 | C42: MRI_0031 | D42: MRI Scanner | E42: Radiology | F42: 5000 | G42: 90000 | H42: 85000 | I42: 0.23 | J42: =IF(F42=0,0,H42/F42) -> 17 | K42: =IF(J42>=$C$7,"Exceeds Target",IF(J42>=0,"Positive","Negative")) -> Exceeds Target | M42: X-Ray Machine Total | O42: 21199500 | P42: 23.752941 | Q42: 0.61870588
B43: 12/11/2023 | C43: MAMMO_0032 | D43: Mammography Unit | E43: Women's Health | F43: 1000 | G43: 145000 | H43: 144000 | I43: 0.93 | J43: =IF(F43=0,0,H43/F43) -> 144 | K43: =IF(J43>=$C$7,"Exceeds Target",IF(J43>=0,"Positive","Negative")) -> Exceeds Target | M43: Grand Total | O43: 277942500 | P43: 54.325333 | Q43: 0.56893333
B44: 10/27/2023 | C44: CT_0033 | D44: CT Scanner | E44: Radiology | F44: 3000 | G44: 70000 | H44: 67000 | I44: 0.21 | J44: =IF(F44=0,0,H44/F44) -> 22.333333 | K44: =IF(J44>=$C$7,"Exceeds Target",IF(J44>=0,"Positive","Negative")) -> Exceeds Target
B45: 11/25/2023 | C45: MAMMO_0034 | D45: Mammography Unit | E45: Women's Health | F45: 1000 | G45: 150000 | H45: 149000 | I45: 0.48 | J45: =IF(F45=0,0,H45/F45) -> 149 | K45: =IF(J45>=$C$7,"Exceeds Target",IF(J45>=0,"Positive","Negative")) -> Exceeds Target
B46: 8/2/2023 | C46: CT_0035 | D46: CT Scanner | E46: Radiology | F46: 3000 | G46: 60000 | H46: 57000 | I46: 0.95 | J46: =IF(F46=0,0,H46/F46) -> 19 | K46: =IF(J46>=$C$7,"Exceeds Target",IF(J46>=0,"Positive","Negative")) -> Exceeds Target
B47: 5/3/2023 | C47: MRI_0036 | D47: MRI Scanner | E47: Radiology | F47: 5000 | G47: 90000 | H47: 85000 | I47: 0.19 | J47: =IF(F47=0,0,H47/F47) -> 17 | K47: =IF(J47>=$C$7,"Exceeds Target",IF(J47>=0,"Positive","Negative")) -> Exceeds Target
B48: 11/28/2023 | C48: CT_0037 | D48: CT Scanner | E48: Radiology | F48: 3000 | G48: 130000 | H48: 127000 | I48: 0.75 | J48: =IF(F48=0,0,H48/F48) -> 42.333333 | K48: =IF(J48>=$C$7,"Exceeds Target",IF(J48>=0,"Positive","Negative")) -> Exceeds Target
B49: 9/13/2023 | C49: XRAY_0038 | D49: X-Ray Machine | E49: Radiology | F49: 1500 | G49: 46000 | H49: 44500 | I49: 0.8 | J49: =IF(F49=0,0,H49/F49) -> 29.666667 | K49: =IF(J49>=$C$7,"Exceeds Target",IF(J49>=0,"Positive","Negative")) -> Exceeds Target
B50: 10/23/2023 | C50: XRAY_0039 | D50: X-Ray Machine | E50: Radiology | F50: 1500 | G50: 26000 | H50: 24500 | I50: 0.86 | J50: =IF(F50=0,0,H50/F50) -> 16.333333 | K50: =IF(J50>=$C$7,"Exceeds Target",IF(J50>=0,"Positive","Negative")) -> Exceeds Target
B51: 8/11/2023 | C51: MRI_0040 | D51: MRI Scanner | E51: Radiology | F51: 5000 | G51: 120000 | H51: 115000 | I51: 0.22 | J51: =IF(F51=0,0,H51/F51) -> 23 | K51: =IF(J51>=$C$7,"Exceeds Target",IF(J51>=0,"Positive","Negative")) -> Exceeds Target
B52: 9/23/2023 | C52: US_0041 | D52: Ultrasound | E52: Radiology | F52: 1000 | G52: 120000 | H52: 119000 | I52: 0.77 | J52: =IF(F52=0,0,H52/F52) -> 119 | K52: =IF(J52>=$C$7,"Exceeds Target",IF(J52>=0,"Positive","Negative")) -> Exceeds Target
B53: 6/20/2023 | C53: MAMMO_0042 | D53: Mammography Unit | E53: Women's Health | F53: 1000 | G53: 115000 | H53: 114000 | I53: 0.95 | J53: =IF(F53=0,0,H53/F53) -> 114 | K53: =IF(J53>=$C$7,"Exceeds Target",IF(J53>=0,"Positive","Negative")) -> Exceeds Target
B54: 10/13/2023 | C54: MAMMO_0043 | D54: Mammography Unit | E54: Women's Health | F54: 1000 | G54: 150000 | H54: 149000 | I54: 0.3 | J54: =IF(F54=0,0,H54/F54) -> 149 | K54: =IF(J54>=$C$7,"Exceeds Target",IF(J54>=0,"Positive","Negative")) -> Exceeds Target
B55: 6/29/2023 | C55: XRAY_0044 | D55: X-Ray Machine | E55: Radiology | F55: 1500 | G55: 36000 | H55: 34500 | I55: 0.52 | J55: =IF(F55=0,0,H55/F55) -> 23 | K55: =IF(J55>=$C$7,"Exceeds Target",IF(J55>=0,"Positive","Negative")) -> Exceeds Target
... B3011: 7/27/2023 | C3011: MAMMO_3000 | D3011: Mammography Unit | E3011: Women's Health | F3011: 1000 | G3011: 125000 | H3011: 124000 | I3011: 0.51 | J3011: =IF(F3011=0,0,H3011/F3011) -> 124 | K3011: =IF(J3011>=$C$7,"Exceeds Target",IF(J3011>=0,"Positive","Negative")) -> Exceeds Target
B3013: KEY METRICS SUMMARY
B3015: Total Operating Costs | C3015: =SUM(F12:F3011) -> 6821500
B3016: Total Revenue | C3016: =SUM(G12:G3011) -> 284764000
B3017: Total Net Profit | C3017: =SUM(H12:H3011) -> 277942500
B3018: Average ROI | C3018: =AVERAGE(J12:J3011) -> 54.325333
B3019: Equipment Exceeding Target | C3019: =COUNTIF(K12:K3011,"Exceeds Target") -> 3000
B3020: Total Positive ROI Records | C3020: =COUNTIF(K12:K3011,"Positive")+COUNTIF(K12:K3011,"Exceeds Target") -> 3000
B3022: CHARTS & VISUALIZATIONS
B3024: Equipment Type Summary | G3024: Department Performance | K3024: ROI Status
B3025: Equipment Type | C3025: Total Operating Cost | D3025: Total Revenue | E3025: Total Profit | G3025: Department | H3025: Avg Utilization | I3025: Total Profit | K3025: Status | L3025: Count
B3026: MRI Scanner | C3026: =SUMIF($D$12:$D$3011,"MRI Scanner",$F$12:$F$3011) -> 3005000 | D3026: =SUMIF($D$12:$D$3011,"MRI Scanner",$G$12:$G$3011) -> 54930000 | E3026: =SUMIF($D$12:$D$3011,"MRI Scanner",$H$12:$H$3011) -> 51925000 | G3026: Radiology | H3026: =AVERAGEIF($E$12:$E$3011,"Radiology",$I$12:$I$3011) -> 0.55358362 | I3026: =SUMIF($E$12:$E$3011,"Radiology",$H$12:$H$3011) -> 219623500 | K3026: Exceeds Target | L3026: =COUNTIF($K$12:$K$3011,"Exceeds Target") -> 3000
B3027: CT Scanner | C3027: =SUMIF($D$12:$D$3011,"CT Scanner",$F$12:$F$3011) -> 1680000 | D3027: =SUMIF($D$12:$D$3011,"CT Scanner",$G$12:$G$3011) -> 101220000 | E3027: =SUMIF($D$12:$D$3011,"CT Scanner",$H$12:$H$3011) -> 99540000 | G3027: Women's Health | H3027: =AVERAGEIF($E$12:$E$3011,"Women's Health",$I$12:$I$3011) -> 0.62378049 | I3027: =SUMIF($E$12:$E$3011,"Women's Health",$H$12:$H$3011) -> 58319000 | K3027: Positive | L3027: =COUNTIF($K$12:$K$3011,"Positive") -> 0
B3028: X-Ray Machine | C3028: =SUMIF($D$12:$D$3011,"X-Ray Machine",$F$12:$F$3011) -> 892500 | D3028: =SUMIF($D$12:$D$3011,"X-Ray Machine",$G$12:$G$3011) -> 22092000 | E3028: =SUMIF($D$12:$D$3011,"X-Ray Machine",$H$12:$H$3011) -> 21199500 | K3028: Negative | L3028: =COUNTIF($K$12:$K$3011,"Negative") -> 0
B3029: Mammography Unit | C3029: =SUMIF($D$12:$D$3011,"Mammography Unit",$F$12:$F$3011) -> 656000 | D3029: =SUMIF($D$12:$D$3011,"Mammography Unit",$G$12:$G$3011) -> 58975000 | E3029: =SUMIF($D$12:$D$3011,"Mammography Unit",$H$12:$H$3011) -> 58319000
B3032: Equipment Profitability
B3033: Equipment | C3033: Avg ROI % | D3033: Avg Utilization
B3034: MRI Scanner | C3034: =AVERAGEIF($D$12:$D$3011,"MRI Scanner",$J$12:$J$3011) -> 17.279534 | D3034: =AVERAGEIF($D$12:$D$3011,"MRI Scanner",$I$12:$I$3011) -> 0.19204659
B3035: CT Scanner | C3035: =AVERAGEIF($D$12:$D$3011,"CT Scanner",$J$12:$J$3011) -> 59.25 | D3035: =AVERAGEIF($D$12:$D$3011,"CT Scanner",$I$12:$I$3011) -> 0.61048214
B3036: X-Ray Machine | C3036: =AVERAGEIF($D$12:$D$3011,"X-Ray Machine",$J$12:$J$3011) -> 23.752941 | D3036: =AVERAGEIF($D$12:$D$3011,"X-Ray Machine",$I$12:$I$3011) -> 0.61870588
B3037: Mammography Unit | C3037: =AVERAGEIF($D$12:$D$3011,"Mammography Unit",$J$12:$J$3011) -> 88.900915 | D3037: =AVERAGEIF($D$12:$D$3011,"Mammography Unit",$I$12:$I$3011) -> 0.62378049
B3046: 💡 ANALYSIS COMPLETE: This sheet contains 36 records of medical equipment performance with automated ROI calculations, 3 pivot tables, and 4 visualization charts.

Sheet Utilization_Analysis
B2: EQUIPMENT UTILIZATION METRIC ANALYSIS - 2023
B4: UTILIZATION RATE CALCULATIONS
B6: Equipment Type | C6: Avg Utilization % | D6: Max Utilization % | E6: Min Utilization % | F6: Std Deviation | G6: Total Records | H6: Efficiency Score
B7: MRI Scanner | C7: =AVERAGEIF(ROI_Analysis!$D$12:$D$3011,"MRI Scanner",ROI_Analysis!$I$12:$I$3011) -> 0.19204659 | D7: =_xlfn.MAXIFS(ROI_Analysis!$I$12:$I$3011,ROI_Analysis!$D$12:$D$3011,"MRI Scanner") -> 0.5 | E7: =_xlfn.MINIFS(ROI_Analysis!$I$12:$I$3011,ROI_Analysis!$D$12:$D$3011,"MRI Scanner") -> 0.03 | F7: =(D7-E7)/4 -> 0.1175 | G7: =COUNTIF(ROI_Analysis!$D$12:$D$3011,"MRI Scanner") -> 601 | H7: =C7 -> 0.19204659
B8: CT Scanner | C8: =AVERAGEIF(ROI_Analysis!$D$12:$D$3011,"CT Scanner",ROI_Analysis!$I$12:$I$3011) -> 0.61048214 | D8: =_xlfn.MAXIFS(ROI_Analysis!$I$12:$I$3011,ROI_Analysis!$D$12:$D$3011,"CT Scanner") -> 1 | E8: =_xlfn.MINIFS(ROI_Analysis!$I$12:$I$3011,ROI_Analysis!$D$12:$D$3011,"CT Scanner") -> 0.18 | F8: =(D8-E8)/4 -> 0.205 | G8: =COUNTIF(ROI_Analysis!$D$12:$D$3011,"CT Scanner") -> 560 | H8: =C8 -> 0.61048214
B9: X-Ray Machine | C9: =AVERAGEIF(ROI_Analysis!$D$12:$D$3011,"X-Ray Machine",ROI_Analysis!$I$12:$I$3011) -> 0.61870588 | D9: =_xlfn.MAXIFS(ROI_Analysis!$I$12:$I$3011,ROI_Analysis!$D$12:$D$3011,"X-Ray Machine") -> 1 | E9: =_xlfn.MINIFS(ROI_Analysis!$I$12:$I$3011,ROI_Analysis!$D$12:$D$3011,"X-Ray Machine") -> 0.16 | F9: =(D9-E9)/4 -> 0.21 | G9: =COUNTIF(ROI_Analysis!$D$12:$D$3011,"X-Ray Machine") -> 595 | H9: =C9 -> 0.61870588
B10: Mammography Unit | C10: =AVERAGEIF(ROI_Analysis!$D$12:$D$3011,"Mammography Unit",ROI_Analysis!$I$12:$I$3011) -> 0.62378049 | D10: =_xlfn.MAXIFS(ROI_Analysis!$I$12:$I$3011,ROI_Analysis!$D$12:$D$3011,"Mammography Unit") -> 1 | E10: =_xlfn.MINIFS(ROI_Analysis!$I$12:$I$3011,ROI_Analysis!$D$12:$D$3011,"Mammography Unit") -> 0.15 | F10: =(D10-E10)/4 -> 0.2125 | G10: =COUNTIF(ROI_Analysis!$D$12:$D$3011,"Mammography Unit") -> 656 | H10: =C10 -> 0.62378049
B12: PERFORMANCE BENCHMARKING
B14: Industry Benchmarks
B15: Equipment Type | C15: Target Utilization | D15: Actual Utilization | E15: Variance | F15: Performance Status | G15: Gap Analysis
B16: MRI Scanner | C16: 0.65 | D16: =C7 -> 0.19204659 | E16: =D16-C16 -> -0.45795341 | F16: =IF(E16>=0,"Meets/Exceeds Target","Below Target") -> Below Target | G16: =ABS(E16) -> 0.45795341
B17: CT Scanner | C17: 0.7 | D17: =C8 -> 0.61048214 | E17: =D17-C17 -> -0.089517857 | F17: =IF(E17>=0,"Meets/Exceeds Target","Below Target") -> Below Target | G17: =ABS(E17) -> 0.089517857
B18: X-Ray Machine | C18: 0.75 | D18: =C9 -> 0.61870588 | E18: =D18-C18 -> -0.13129412 | F18: =IF(E18>=0,"Meets/Exceeds Target","Below Target") -> Below Target | G18: =ABS(E18) -> 0.13129412
B19: Mammography Unit | C19: 0.7 | D19: =C10 -> 0.62378049 | E19: =D19-C19 -> -0.076219512 | F19: =IF(E19>=0,"Meets/Exceeds Target","Below Target") -> Below Target | G19: =ABS(E19) -> 0.076219512
B21: EQUIPMENT EFFICIENCY ANALYSIS
B23: Equipment Type | C23: Avg Operating Hours/Day | D23: Avg Available Hours/Day | E23: Idle Time % | F23: Productivity Score | G23: Avg Procedures/Day | H23: Revenue per Hour
B24: MRI Scanner | C24: N/A | D24: N/A | E24: =1-C7 -> 0.80795341 | F24: =C7 -> 0.19204659 | G24: =AVERAGEIF(ROI_Analysis!$D$12:$D$3011,"MRI Scanner",ROI_Analysis!$H$12:$H$3011) -> 86397.671 | H24: =AVERAGEIF(ROI_Analysis!$D$12:$D$3011,"MRI Scanner",ROI_Analysis!$G$12:$G$3011) -> 91397.671
B25: CT Scanner | C25: N/A | D25: N/A | E25: =1-C8 -> 0.38951786 | F25: =C8 -> 0.61048214 | G25: =AVERAGEIF(ROI_Analysis!$D$12:$D$3011,"CT Scanner",ROI_Analysis!$H$12:$H$3011) -> 177750 | H25: =AVERAGEIF(ROI_Analysis!$D$12:$D$3011,"CT Scanner",ROI_Analysis!$G$12:$G$3011) -> 180750
B26: X-Ray Machine | C26: N/A | D26: N/A | E26: =1-C9 -> 0.38129412 | F26: =C9 -> 0.61870588 | G26: =AVERAGEIF(ROI_Analysis!$D$12:$D$3011,"X-Ray Machine",ROI_Analysis!$H$12:$H$3011) -> 35629.412 | H26: =AVERAGEIF(ROI_Analysis!$D$12:$D$3011,"X-Ray Machine",ROI_Analysis!$G$12:$G$3011) -> 37129.412
B27: Mammography Unit | C27: N/A | D27: N/A | E27: =1-C10 -> 0.37621951 | F27: =C10 -> 0.62378049 | G27: =AVERAGEIF(ROI_Analysis!$D$12:$D$3011,"Mammography Unit",ROI_Analysis!$H$12:$H$3011) -> 88900.915 | H27: =AVERAGEIF(ROI_Analysis!$D$12:$D$3011,"Mammography Unit",ROI_Analysis!$G$12:$G$3011) -> 89900.915
B29: KEY INSIGHTS & RECOMMENDATIONS
B31: Overall Fleet Metrics
B32: Metric | C32: Value
B33: Fleet Average Utilization | C33: =AVERAGE(C7:C10) -> 0.51125378
B34: Best Performing Equipment | C34: =INDEX(B7:B10,MATCH(MAX(C7:C10),C7:C10,0)) -> Mammography Unit
B35: Lowest Performing Equipment | C35: =INDEX(B7:B10,MATCH(MIN(C7:C10),C7:C10,0)) -> MRI Scanner
B36: Equipment Below Target | C36: =COUNTIF(F16:F19,"Below Target") -> 4
B37: Average Gap to Target | C37: =AVERAGE(G16:G19) -> 0.18874622
B38: Highest Revenue/Hour Equipment | C38: =INDEX(B24:B27,MATCH(MAX(H24:H27),H24:H27,0)) -> CT Scanner
B40: ACTIONABLE RECOMMENDATIONS
B42: 1. MRI Scanner: Increase utilization by 46% to reach 65% target
B43: - Consider extended operating hours
B44: - Improve scheduling efficiency
B45: - Marketing to increase patient volume
B46: 0
B47: 2. CT Scanner: Close 9% gap to reach 70% target
B48: - Optimize appointment scheduling
B49: - Reduce idle time between procedures
B50: 0
B51: 3. X-Ray Machine: Improve by 13% to reach 75% target
B52: - Fastest turnaround equipment
B53: - Streamline patient flow
B54: 0
B55: 4. Mammography Unit: Close 8% gap to reach 70% target
B56: - Best performing equipment type
B57: - Maintain current practices

Sheet Sheet2
